README.rst
httpie_ntlm.py
setup.py
httpie_ntlm.egg-info/PKG-INFO
httpie_ntlm.egg-info/SOURCES.txt
httpie_ntlm.egg-info/dependency_links.txt
httpie_ntlm.egg-info/entry_points.txt
httpie_ntlm.egg-info/not-zip-safe
httpie_ntlm.egg-info/requires.txt
httpie_ntlm.egg-info/top_level.txt